udgram.py
udgram-1.1.9.dist-info/WHEEL
udgram-1.1.9.dist-info/METADATA
udgram-1.1.9.dist-info/RECORD
